{
  "versions": [
    {
      "key": "python3.14-nodejs24",
      "python": "3.14",
      "python_canonical": "3.14.0",
      "python_image": "3.14.0-trixie",
      "nodejs": "24",
      "nodejs_canonical": "24.11.1",
      "distro": "trixie",
      "platforms": [
        "linux/amd64",
        "linux/arm64"
      ],
      "digest": "sha256:cb59fa12d644a504f8c2c3a37d8a82d9820158a26dd847966f7dda135f5001d3"
    },
    {
      "key": "python3.14-nodejs24-bookworm",
      "python": "3.14",
      "python_canonical": "3.14.0",
      "python_image": "3.14.0-bookworm",
      "nodejs": "24",
      "nodejs_canonical": "24.11.1",
      "distro": "bookworm",
      "platforms": [
        "linux/amd64",
        "linux/arm64"
      ],
      "digest": "sha256:7a8dc6213478241c1dbd3241a712d6cc589f5bd2d7fe585ba7101ffb4b9bc566"
    },
    {
      "key": "python3.14-nodejs24-slim",
      "python": "3.14",
      "python_canonical": "3.14.0",
      "python_image": "3.14.0-slim",
      "nodejs": "24",
      "nodejs_canonical": "24.11.1",
      "distro": "slim",
      "platforms": [
        "linux/amd64",
        "linux/arm64"
      ],
      "digest": "sha256:e6a7777b603499513f363adbd432a8f063986ab155a71cfba94b9b00b3125814"
    },
    {
      "key": "python3.13-nodejs24",
      "python": "3.13",
      "python_canonical": "3.13.9",
      "python_image": "3.13.9-trixie",
      "nodejs": "24",
      "nodejs_canonical": "24.11.1",
      "distro": "trixie",
      "platforms": [
        "linux/amd64",
        "linux/arm64"
      ],
      "digest": "sha256:953dce7dec568fe15369fc24b5e5fab8e17f24880354366f099d640a8fae22e0"
    },
    {
      "key": "python3.13-nodejs24-bookworm",
      "python": "3.13",
      "python_canonical": "3.13.9",
      "python_image": "3.13.9-bookworm",
      "nodejs": "24",
      "nodejs_canonical": "24.11.1",
      "distro": "bookworm",
      "platforms": [
        "linux/amd64",
        "linux/arm64"
      ],
      "digest": "sha256:62384db86d91ea7f43f82c706f52df1cb4417d885e43f2341694666c9a150011"
    },
    {
      "key": "python3.13-nodejs24-slim",
      "python": "3.13",
      "python_canonical": "3.13.9",
      "python_image": "3.13.9-slim",
      "nodejs": "24",
      "nodejs_canonical": "24.11.1",
      "distro": "slim",
      "platforms": [
        "linux/amd64",
        "linux/arm64"
      ],
      "digest": "sha256:a4d1c2a7bc98b4b5775b492c446dfb41fc1a745a31786ed9893961ce10cbcaf2"
    },
    {
      "key": "python3.12-nodejs24",
      "python": "3.12",
      "python_canonical": "3.12.12",
      "python_image": "3.12.12-trixie",
      "nodejs": "24",
      "nodejs_canonical": "24.11.1",
      "distro": "trixie",
      "platforms": [
        "linux/amd64",
        "linux/arm64"
      ],
      "digest": "sha256:3e70de88edb4624dbc4d39e89ae52c477b53318847dc91a4b17ebc19ab497001"
    },
    {
      "key": "python3.12-nodejs24-bookworm",
      "python": "3.12",
      "python_canonical": "3.12.12",
      "python_image": "3.12.12-bookworm",
      "nodejs": "24",
      "nodejs_canonical": "24.11.1",
      "distro": "bookworm",
      "platforms": [
        "linux/amd64",
        "linux/arm64"
      ],
      "digest": "sha256:a3b4ba8e3723fcf46d26b34fb62ca805f1694292fa2e7e3a030d48841841335c"
    },
    {
      "key": "python3.12-nodejs24-slim",
      "python": "3.12",
      "python_canonical": "3.12.12",
      "python_image": "3.12.12-slim",
      "nodejs": "24",
      "nodejs_canonical": "24.11.1",
      "distro": "slim",
      "platforms": [
        "linux/amd64",
        "linux/arm64"
      ],
      "digest": "sha256:cd64267953a0a13f7ca2eaa8f721cf0f48402214c3bf724fb0fa41e61fd823bb"
    },
    {
      "key": "python3.11-nodejs24",
      "python": "3.11",
      "python_canonical": "3.11.14",
      "python_image": "3.11.14-trixie",
      "nodejs": "24",
      "nodejs_canonical": "24.11.1",
      "distro": "trixie",
      "platforms": [
        "linux/amd64",
        "linux/arm64"
      ],
      "digest": "sha256:4a02f0a9d70c191bf21720df95ac09e5fd2ef7ec02baaf73e2c84592363e9b9b"
    },
    {
      "key": "python3.11-nodejs24-bookworm",
      "python": "3.11",
      "python_canonical": "3.11.14",
      "python_image": "3.11.14-bookworm",
      "nodejs": "24",
      "nodejs_canonical": "24.11.1",
      "distro": "bookworm",
      "platforms": [
        "linux/amd64",
        "linux/arm64"
      ],
      "digest": "sha256:3845ae6d4a230c8395ed7d1f354416baa2c2f92b53e61a3b734659cf6a8fb9d0"
    },
    {
      "key": "python3.11-nodejs24-slim",
      "python": "3.11",
      "python_canonical": "3.11.14",
      "python_image": "3.11.14-slim",
      "nodejs": "24",
      "nodejs_canonical": "24.11.1",
      "distro": "slim",
      "platforms": [
        "linux/amd64",
        "linux/arm64"
      ],
      "digest": "sha256:c497ea02db18b36a36be691ce1a512bb14772e1acb9314071884dd77c71e8a62"
    },
    {
      "key": "python3.10-nodejs24",
      "python": "3.10",
      "python_canonical": "3.10.19",
      "python_image": "3.10.19-trixie",
      "nodejs": "24",
      "nodejs_canonical": "24.11.1",
      "distro": "trixie",
      "platforms": [
        "linux/amd64",
        "linux/arm64"
      ],
      "digest": "sha256:49f0327d24f124bef5ddf4c9bff35ea036ec7b2894e483414566ad17e760816d"
    },
    {
      "key": "python3.10-nodejs24-bookworm",
      "python": "3.10",
      "python_canonical": "3.10.19",
      "python_image": "3.10.19-bookworm",
      "nodejs": "24",
      "nodejs_canonical": "24.11.1",
      "distro": "bookworm",
      "platforms": [
        "linux/amd64",
        "linux/arm64"
      ],
      "digest": "sha256:983ca20b01b8fd2563fe8ff5ffc771a11967853e94360feb955925a031c4e42f"
    },
    {
      "key": "python3.10-nodejs24-slim",
      "python": "3.10",
      "python_canonical": "3.10.19",
      "python_image": "3.10.19-slim",
      "nodejs": "24",
      "nodejs_canonical": "24.11.1",
      "distro": "slim",
      "platforms": [
        "linux/amd64",
        "linux/arm64"
      ],
      "digest": "sha256:c37a19799c07878332b4a4ebd387a90cc4c82ff2cdb953716e4e341ae0025e0f"
    }
  ]
}