{
  "versions": [
    {
      "key": "python3.14-nodejs25",
      "python": "3.14",
      "python_canonical": "3.14.0",
      "python_image": "3.14.0-trixie",
      "nodejs": "25",
      "nodejs_canonical": "25.1.0",
      "distro": "trixie",
      "platforms": [
        "linux/amd64",
        "linux/arm64"
      ],
      "digest": "sha256:df19194bac9153fb45d7041dd41825c3acf0269622901e23037109654ef8cb90"
    },
    {
      "key": "python3.14-nodejs25-bookworm",
      "python": "3.14",
      "python_canonical": "3.14.0",
      "python_image": "3.14.0-bookworm",
      "nodejs": "25",
      "nodejs_canonical": "25.1.0",
      "distro": "bookworm",
      "platforms": [
        "linux/amd64",
        "linux/arm64"
      ],
      "digest": "sha256:963f66010f9fc5f1e38b3f75268435e3a18fd6295ff8ab8bd696832ef68decf3"
    },
    {
      "key": "python3.14-nodejs25-slim",
      "python": "3.14",
      "python_canonical": "3.14.0",
      "python_image": "3.14.0-slim",
      "nodejs": "25",
      "nodejs_canonical": "25.1.0",
      "distro": "slim",
      "platforms": [
        "linux/amd64",
        "linux/arm64"
      ],
      "digest": "sha256:00c85336cd218e76647ff70c6b84effc30cd884eb13365069e1e1e41af76ba6f"
    },
    {
      "key": "python3.14-nodejs25-alpine",
      "python": "3.14",
      "python_canonical": "3.14.0",
      "python_image": "3.14.0-alpine",
      "nodejs": "25",
      "nodejs_canonical": "25.1.0",
      "distro": "alpine",
      "platforms": [
        "linux/amd64"
      ],
      "digest": "sha256:337bf13896038b90c4bbe6d84a62c0f065d2193d1d1e4060365a7f2d0e758c11"
    },
    {
      "key": "python3.14-nodejs24",
      "python": "3.14",
      "python_canonical": "3.14.0",
      "python_image": "3.14.0-trixie",
      "nodejs": "24",
      "nodejs_canonical": "24.11.0",
      "distro": "trixie",
      "platforms": [
        "linux/amd64",
        "linux/arm64"
      ],
      "digest": "sha256:fc5b280a42956e45b0e5495eab675998820b03e3755430f689121c80c8e604a2"
    },
    {
      "key": "python3.14-nodejs24-bookworm",
      "python": "3.14",
      "python_canonical": "3.14.0",
      "python_image": "3.14.0-bookworm",
      "nodejs": "24",
      "nodejs_canonical": "24.11.0",
      "distro": "bookworm",
      "platforms": [
        "linux/amd64",
        "linux/arm64"
      ],
      "digest": "sha256:be7f68ca896920992cfc682d1072fff1612097b2a2569915d136050e49aad971"
    },
    {
      "key": "python3.14-nodejs24-slim",
      "python": "3.14",
      "python_canonical": "3.14.0",
      "python_image": "3.14.0-slim",
      "nodejs": "24",
      "nodejs_canonical": "24.11.0",
      "distro": "slim",
      "platforms": [
        "linux/amd64",
        "linux/arm64"
      ],
      "digest": "sha256:3bb89500b134aa027a280ccf47aa024a5a2c7c57578a9763304498f7b5279ccd"
    },
    {
      "key": "python3.14-nodejs24-alpine",
      "python": "3.14",
      "python_canonical": "3.14.0",
      "python_image": "3.14.0-alpine",
      "nodejs": "24",
      "nodejs_canonical": "24.11.0",
      "distro": "alpine",
      "platforms": [
        "linux/amd64"
      ],
      "digest": "sha256:85ef2631f1f5fc3961c9f03b49216ff8fb9fcded14286ae882122d61b7fa98ca"
    },
    {
      "key": "python3.14-nodejs22",
      "python": "3.14",
      "python_canonical": "3.14.0",
      "python_image": "3.14.0-trixie",
      "nodejs": "22",
      "nodejs_canonical": "22.21.1",
      "distro": "trixie",
      "platforms": [
        "linux/amd64",
        "linux/arm64"
      ],
      "digest": "sha256:7d541945e05e56f40e7e59331dc04bf206b79b9051445d2407fade132036f220"
    },
    {
      "key": "python3.14-nodejs22-bookworm",
      "python": "3.14",
      "python_canonical": "3.14.0",
      "python_image": "3.14.0-bookworm",
      "nodejs": "22",
      "nodejs_canonical": "22.21.1",
      "distro": "bookworm",
      "platforms": [
        "linux/amd64",
        "linux/arm64"
      ],
      "digest": "sha256:3f3bf910f7b1e7dae6ed9399a10298105c19c26df2fb6ba257173b4164e08dc6"
    },
    {
      "key": "python3.14-nodejs22-slim",
      "python": "3.14",
      "python_canonical": "3.14.0",
      "python_image": "3.14.0-slim",
      "nodejs": "22",
      "nodejs_canonical": "22.21.1",
      "distro": "slim",
      "platforms": [
        "linux/amd64",
        "linux/arm64"
      ],
      "digest": "sha256:87fe3cd42f0947fd58592cce5313398dd3ae3a95402f2ecd0782a81d1e8b92f6"
    },
    {
      "key": "python3.14-nodejs22-alpine",
      "python": "3.14",
      "python_canonical": "3.14.0",
      "python_image": "3.14.0-alpine",
      "nodejs": "22",
      "nodejs_canonical": "22.21.1",
      "distro": "alpine",
      "platforms": [
        "linux/amd64"
      ],
      "digest": "sha256:1d61dc4310db75148d880d8681e7513d879063539582bf11366e7b3ec20bc179"
    },
    {
      "key": "python3.14-nodejs20",
      "python": "3.14",
      "python_canonical": "3.14.0",
      "python_image": "3.14.0-trixie",
      "nodejs": "20",
      "nodejs_canonical": "20.19.5",
      "distro": "trixie",
      "platforms": [
        "linux/amd64",
        "linux/arm64"
      ],
      "digest": "sha256:1195937f90431980d96f6ca5b9cf6ad52533a74906db28691ec02331ad66bc99"
    },
    {
      "key": "python3.14-nodejs20-bookworm",
      "python": "3.14",
      "python_canonical": "3.14.0",
      "python_image": "3.14.0-bookworm",
      "nodejs": "20",
      "nodejs_canonical": "20.19.5",
      "distro": "bookworm",
      "platforms": [
        "linux/amd64",
        "linux/arm64"
      ],
      "digest": "sha256:14858bfe8ed7aad6213ec7a0ee45eb94dcd69e3b98b81fc5413f4850d3ba199e"
    },
    {
      "key": "python3.14-nodejs20-slim",
      "python": "3.14",
      "python_canonical": "3.14.0",
      "python_image": "3.14.0-slim",
      "nodejs": "20",
      "nodejs_canonical": "20.19.5",
      "distro": "slim",
      "platforms": [
        "linux/amd64",
        "linux/arm64"
      ],
      "digest": "sha256:72a6a9fde281195d739ceb2b288022a49325254a1cbece311f40d37df45a8c17"
    },
    {
      "key": "python3.14-nodejs20-alpine",
      "python": "3.14",
      "python_canonical": "3.14.0",
      "python_image": "3.14.0-alpine",
      "nodejs": "20",
      "nodejs_canonical": "20.19.5",
      "distro": "alpine",
      "platforms": [
        "linux/amd64"
      ],
      "digest": "sha256:8533fa6c2d795e53615e9559538a5826a0f5cea20830d6e635470f0c50d89de4"
    },
    {
      "key": "python3.13-nodejs25",
      "python": "3.13",
      "python_canonical": "3.13.9",
      "python_image": "3.13.9-trixie",
      "nodejs": "25",
      "nodejs_canonical": "25.1.0",
      "distro": "trixie",
      "platforms": [
        "linux/amd64",
        "linux/arm64"
      ],
      "digest": "sha256:b6f09ffbbf284a73a3bd0cc11d560927b5e6040124bf73657bd06299f5c6913b"
    },
    {
      "key": "python3.13-nodejs25-bookworm",
      "python": "3.13",
      "python_canonical": "3.13.9",
      "python_image": "3.13.9-bookworm",
      "nodejs": "25",
      "nodejs_canonical": "25.1.0",
      "distro": "bookworm",
      "platforms": [
        "linux/amd64",
        "linux/arm64"
      ],
      "digest": "sha256:707902e800f11d5364f55aa60aac68a8ace5ed316f9c7680f4c79de2cce3facf"
    },
    {
      "key": "python3.13-nodejs25-slim",
      "python": "3.13",
      "python_canonical": "3.13.9",
      "python_image": "3.13.9-slim",
      "nodejs": "25",
      "nodejs_canonical": "25.1.0",
      "distro": "slim",
      "platforms": [
        "linux/amd64",
        "linux/arm64"
      ],
      "digest": "sha256:0f7a67d5e68ff49f5189eb12f3aaf385bcf7414fa39c70fab75dc3960090bef1"
    },
    {
      "key": "python3.13-nodejs25-alpine",
      "python": "3.13",
      "python_canonical": "3.13.9",
      "python_image": "3.13.9-alpine",
      "nodejs": "25",
      "nodejs_canonical": "25.1.0",
      "distro": "alpine",
      "platforms": [
        "linux/amd64"
      ],
      "digest": "sha256:2750d106eb3075ea4d6acb16dfcb76058d62b4669ebf5f4c89782c3bf95fc468"
    },
    {
      "key": "python3.13-nodejs24",
      "python": "3.13",
      "python_canonical": "3.13.9",
      "python_image": "3.13.9-trixie",
      "nodejs": "24",
      "nodejs_canonical": "24.11.0",
      "distro": "trixie",
      "platforms": [
        "linux/amd64",
        "linux/arm64"
      ],
      "digest": "sha256:170f10a6610bf71898b2394362ee341c295f9d2da7d518f70534d7eef6056e35"
    },
    {
      "key": "python3.13-nodejs24-bookworm",
      "python": "3.13",
      "python_canonical": "3.13.9",
      "python_image": "3.13.9-bookworm",
      "nodejs": "24",
      "nodejs_canonical": "24.11.0",
      "distro": "bookworm",
      "platforms": [
        "linux/amd64",
        "linux/arm64"
      ],
      "digest": "sha256:03105ee89fa29bcafdc5cb7e4c0e29303a940068985a5f2b33bed743be3e3c04"
    },
    {
      "key": "python3.13-nodejs24-slim",
      "python": "3.13",
      "python_canonical": "3.13.9",
      "python_image": "3.13.9-slim",
      "nodejs": "24",
      "nodejs_canonical": "24.11.0",
      "distro": "slim",
      "platforms": [
        "linux/amd64",
        "linux/arm64"
      ],
      "digest": "sha256:978dcc48db96d8305287e1939662c1fe77f43fd3b2dff13ac6eed47248ae698b"
    },
    {
      "key": "python3.13-nodejs24-alpine",
      "python": "3.13",
      "python_canonical": "3.13.9",
      "python_image": "3.13.9-alpine",
      "nodejs": "24",
      "nodejs_canonical": "24.11.0",
      "distro": "alpine",
      "platforms": [
        "linux/amd64"
      ],
      "digest": "sha256:d091e5c996ef7b2062c2ba22ab701ee73f07a7a006bc60143c30f1897fd3a018"
    },
    {
      "key": "python3.13-nodejs22",
      "python": "3.13",
      "python_canonical": "3.13.9",
      "python_image": "3.13.9-trixie",
      "nodejs": "22",
      "nodejs_canonical": "22.21.1",
      "distro": "trixie",
      "platforms": [
        "linux/amd64",
        "linux/arm64"
      ],
      "digest": "sha256:14f02236f3b28a97458897c550516d9c62323cf2cbaad2bf818393556ebb3368"
    },
    {
      "key": "python3.13-nodejs22-bookworm",
      "python": "3.13",
      "python_canonical": "3.13.9",
      "python_image": "3.13.9-bookworm",
      "nodejs": "22",
      "nodejs_canonical": "22.21.1",
      "distro": "bookworm",
      "platforms": [
        "linux/amd64",
        "linux/arm64"
      ],
      "digest": "sha256:2030c303c2642edd6686b033450e91f3027f14708112ab3272caa3929a215112"
    },
    {
      "key": "python3.13-nodejs22-slim",
      "python": "3.13",
      "python_canonical": "3.13.9",
      "python_image": "3.13.9-slim",
      "nodejs": "22",
      "nodejs_canonical": "22.21.1",
      "distro": "slim",
      "platforms": [
        "linux/amd64",
        "linux/arm64"
      ],
      "digest": "sha256:4c0689ee9ffaa9385cbb1777189d0554afffa05969859ec990f83c3ae97f8c68"
    },
    {
      "key": "python3.13-nodejs22-alpine",
      "python": "3.13",
      "python_canonical": "3.13.9",
      "python_image": "3.13.9-alpine",
      "nodejs": "22",
      "nodejs_canonical": "22.21.1",
      "distro": "alpine",
      "platforms": [
        "linux/amd64"
      ],
      "digest": "sha256:7386f5789d3fabc9ad9ca2a6aa25f23176f6e64fb3c2b568451940a6b675f38b"
    },
    {
      "key": "python3.13-nodejs20",
      "python": "3.13",
      "python_canonical": "3.13.9",
      "python_image": "3.13.9-trixie",
      "nodejs": "20",
      "nodejs_canonical": "20.19.5",
      "distro": "trixie",
      "platforms": [
        "linux/amd64",
        "linux/arm64"
      ],
      "digest": "sha256:a75062d67bd6e83bf9723dbbfbba67aa8e620b63127ffe542915f0f086f55626"
    },
    {
      "key": "python3.13-nodejs20-bookworm",
      "python": "3.13",
      "python_canonical": "3.13.9",
      "python_image": "3.13.9-bookworm",
      "nodejs": "20",
      "nodejs_canonical": "20.19.5",
      "distro": "bookworm",
      "platforms": [
        "linux/amd64",
        "linux/arm64"
      ],
      "digest": "sha256:945965af8bf518acaa8834f9f3bb9417ee7a90e126b57cafcb074d418857a6fd"
    },
    {
      "key": "python3.13-nodejs20-slim",
      "python": "3.13",
      "python_canonical": "3.13.9",
      "python_image": "3.13.9-slim",
      "nodejs": "20",
      "nodejs_canonical": "20.19.5",
      "distro": "slim",
      "platforms": [
        "linux/amd64",
        "linux/arm64"
      ],
      "digest": "sha256:87cd85d90c83be6f007899a53b4b0aeb068b3531b60947aa9617e0c351a65432"
    },
    {
      "key": "python3.13-nodejs20-alpine",
      "python": "3.13",
      "python_canonical": "3.13.9",
      "python_image": "3.13.9-alpine",
      "nodejs": "20",
      "nodejs_canonical": "20.19.5",
      "distro": "alpine",
      "platforms": [
        "linux/amd64"
      ],
      "digest": "sha256:cc170e60cea9261effa8f73128dfdaaa3478626a2783dc25d08d288863d6b73a"
    },
    {
      "key": "python3.12-nodejs25",
      "python": "3.12",
      "python_canonical": "3.12.12",
      "python_image": "3.12.12-trixie",
      "nodejs": "25",
      "nodejs_canonical": "25.1.0",
      "distro": "trixie",
      "platforms": [
        "linux/amd64",
        "linux/arm64"
      ],
      "digest": "sha256:99f14a7e6ab8ad101ea766c8d3f08f9351fdb7da9c77d83ad74879688e36ab79"
    },
    {
      "key": "python3.12-nodejs25-bookworm",
      "python": "3.12",
      "python_canonical": "3.12.12",
      "python_image": "3.12.12-bookworm",
      "nodejs": "25",
      "nodejs_canonical": "25.1.0",
      "distro": "bookworm",
      "platforms": [
        "linux/amd64",
        "linux/arm64"
      ],
      "digest": "sha256:b9ed0aaf782aa0a67a65090db0137a3df699b82ff54f2fb42a14b2c0ce441487"
    },
    {
      "key": "python3.12-nodejs25-slim",
      "python": "3.12",
      "python_canonical": "3.12.12",
      "python_image": "3.12.12-slim",
      "nodejs": "25",
      "nodejs_canonical": "25.1.0",
      "distro": "slim",
      "platforms": [
        "linux/amd64",
        "linux/arm64"
      ],
      "digest": "sha256:97fd1416b7318b8e2aee22c4c9b0000455c532c73ea97c462c0f6aa9271aa636"
    },
    {
      "key": "python3.12-nodejs25-alpine",
      "python": "3.12",
      "python_canonical": "3.12.12",
      "python_image": "3.12.12-alpine",
      "nodejs": "25",
      "nodejs_canonical": "25.1.0",
      "distro": "alpine",
      "platforms": [
        "linux/amd64"
      ],
      "digest": "sha256:eec378faf92f3c9cd380d96eb4872880525ae331b97c2c94d178e20891c97bd4"
    },
    {
      "key": "python3.12-nodejs24",
      "python": "3.12",
      "python_canonical": "3.12.12",
      "python_image": "3.12.12-trixie",
      "nodejs": "24",
      "nodejs_canonical": "24.11.0",
      "distro": "trixie",
      "platforms": [
        "linux/amd64",
        "linux/arm64"
      ],
      "digest": "sha256:fc32d7b2298ffc242b7c9cd6199b9e23cdf56ca9f5f7edb5a545edc043779760"
    },
    {
      "key": "python3.12-nodejs24-bookworm",
      "python": "3.12",
      "python_canonical": "3.12.12",
      "python_image": "3.12.12-bookworm",
      "nodejs": "24",
      "nodejs_canonical": "24.11.0",
      "distro": "bookworm",
      "platforms": [
        "linux/amd64",
        "linux/arm64"
      ],
      "digest": "sha256:fc7f0bada31a3eb14da831d600540018d76aaedbdf1da71d8bb269ca89436b29"
    },
    {
      "key": "python3.12-nodejs24-slim",
      "python": "3.12",
      "python_canonical": "3.12.12",
      "python_image": "3.12.12-slim",
      "nodejs": "24",
      "nodejs_canonical": "24.11.0",
      "distro": "slim",
      "platforms": [
        "linux/amd64",
        "linux/arm64"
      ],
      "digest": "sha256:8aec0e2df9af64d61b9b9a6381296e8503ceeec70e8d86edc4ff924b4b4af852"
    },
    {
      "key": "python3.12-nodejs24-alpine",
      "python": "3.12",
      "python_canonical": "3.12.12",
      "python_image": "3.12.12-alpine",
      "nodejs": "24",
      "nodejs_canonical": "24.11.0",
      "distro": "alpine",
      "platforms": [
        "linux/amd64"
      ],
      "digest": "sha256:8d5c0f0db72815b8eb0f43994989814d7c50479ab31d08e44fa4321761e3d3c3"
    },
    {
      "key": "python3.12-nodejs22",
      "python": "3.12",
      "python_canonical": "3.12.12",
      "python_image": "3.12.12-trixie",
      "nodejs": "22",
      "nodejs_canonical": "22.21.1",
      "distro": "trixie",
      "platforms": [
        "linux/amd64",
        "linux/arm64"
      ],
      "digest": "sha256:0894d6f352d75acd5450c77529448d4fd2f4b780ea45bb14b47a8a83a543d0f1"
    },
    {
      "key": "python3.12-nodejs22-bookworm",
      "python": "3.12",
      "python_canonical": "3.12.12",
      "python_image": "3.12.12-bookworm",
      "nodejs": "22",
      "nodejs_canonical": "22.21.1",
      "distro": "bookworm",
      "platforms": [
        "linux/amd64",
        "linux/arm64"
      ],
      "digest": "sha256:a458d2bd6ce82eb73b46ece868bfe2476068954b4be5fa872c48b752cf00db91"
    },
    {
      "key": "python3.12-nodejs22-slim",
      "python": "3.12",
      "python_canonical": "3.12.12",
      "python_image": "3.12.12-slim",
      "nodejs": "22",
      "nodejs_canonical": "22.21.1",
      "distro": "slim",
      "platforms": [
        "linux/amd64",
        "linux/arm64"
      ],
      "digest": "sha256:fb4f82bb36d64999eebb6da477b8a09622d2afe8c3b2013e3db5dd899341da7e"
    },
    {
      "key": "python3.12-nodejs22-alpine",
      "python": "3.12",
      "python_canonical": "3.12.12",
      "python_image": "3.12.12-alpine",
      "nodejs": "22",
      "nodejs_canonical": "22.21.1",
      "distro": "alpine",
      "platforms": [
        "linux/amd64"
      ],
      "digest": "sha256:aa0dbbb58ea7bb056b73cb2c41da2064edcd4a6fea7395c21659037345abff4f"
    },
    {
      "key": "python3.12-nodejs20",
      "python": "3.12",
      "python_canonical": "3.12.12",
      "python_image": "3.12.12-trixie",
      "nodejs": "20",
      "nodejs_canonical": "20.19.5",
      "distro": "trixie",
      "platforms": [
        "linux/amd64",
        "linux/arm64"
      ],
      "digest": "sha256:7a43d45b970214473fcd55e2a95b65d83e4f7d8b4798fea6e327cb2d02bf93db"
    },
    {
      "key": "python3.12-nodejs20-bookworm",
      "python": "3.12",
      "python_canonical": "3.12.12",
      "python_image": "3.12.12-bookworm",
      "nodejs": "20",
      "nodejs_canonical": "20.19.5",
      "distro": "bookworm",
      "platforms": [
        "linux/amd64",
        "linux/arm64"
      ],
      "digest": "sha256:e0d9b09e515e9b4f1b7b8a0c6ecb53d3a8bd0010de37d082d22efd6da54673ee"
    },
    {
      "key": "python3.12-nodejs20-slim",
      "python": "3.12",
      "python_canonical": "3.12.12",
      "python_image": "3.12.12-slim",
      "nodejs": "20",
      "nodejs_canonical": "20.19.5",
      "distro": "slim",
      "platforms": [
        "linux/amd64",
        "linux/arm64"
      ],
      "digest": "sha256:95530fee2f0e04a0d542fe1b67ebca29c19128a355fd994d73abe8a67deb8797"
    },
    {
      "key": "python3.12-nodejs20-alpine",
      "python": "3.12",
      "python_canonical": "3.12.12",
      "python_image": "3.12.12-alpine",
      "nodejs": "20",
      "nodejs_canonical": "20.19.5",
      "distro": "alpine",
      "platforms": [
        "linux/amd64"
      ],
      "digest": "sha256:e13de5d53cb1acbea98c37214318d8f690ab276ce122b64b83eebf499024bb11"
    },
    {
      "key": "python3.11-nodejs25",
      "python": "3.11",
      "python_canonical": "3.11.14",
      "python_image": "3.11.14-trixie",
      "nodejs": "25",
      "nodejs_canonical": "25.1.0",
      "distro": "trixie",
      "platforms": [
        "linux/amd64",
        "linux/arm64"
      ],
      "digest": "sha256:3afd5263bab07e6d0fe5acb695bbd4514fff1a3d94445869d1342f3d04c5de21"
    },
    {
      "key": "python3.11-nodejs25-bookworm",
      "python": "3.11",
      "python_canonical": "3.11.14",
      "python_image": "3.11.14-bookworm",
      "nodejs": "25",
      "nodejs_canonical": "25.1.0",
      "distro": "bookworm",
      "platforms": [
        "linux/amd64",
        "linux/arm64"
      ],
      "digest": "sha256:ee71f0998b9eeeeeb7e3fe97917a2acdc8ba434f25927a1b52da45ffd3d644bf"
    },
    {
      "key": "python3.11-nodejs25-slim",
      "python": "3.11",
      "python_canonical": "3.11.14",
      "python_image": "3.11.14-slim",
      "nodejs": "25",
      "nodejs_canonical": "25.1.0",
      "distro": "slim",
      "platforms": [
        "linux/amd64",
        "linux/arm64"
      ],
      "digest": "sha256:d34fb69bb3d4ee99dddc8656f1c79db40eb84e5c40f606f77e46ed4beb957952"
    },
    {
      "key": "python3.11-nodejs25-alpine",
      "python": "3.11",
      "python_canonical": "3.11.14",
      "python_image": "3.11.14-alpine",
      "nodejs": "25",
      "nodejs_canonical": "25.1.0",
      "distro": "alpine",
      "platforms": [
        "linux/amd64"
      ],
      "digest": "sha256:7868120a19cf682f754232b2b4649ee517ca02d598492a16e7624bcc91ca4e13"
    },
    {
      "key": "python3.11-nodejs24",
      "python": "3.11",
      "python_canonical": "3.11.14",
      "python_image": "3.11.14-trixie",
      "nodejs": "24",
      "nodejs_canonical": "24.11.0",
      "distro": "trixie",
      "platforms": [
        "linux/amd64",
        "linux/arm64"
      ],
      "digest": "sha256:922aaa15d11b66b30729330170a3f0098925f697cf2dd738e34cbc11e63d72d6"
    },
    {
      "key": "python3.11-nodejs24-bookworm",
      "python": "3.11",
      "python_canonical": "3.11.14",
      "python_image": "3.11.14-bookworm",
      "nodejs": "24",
      "nodejs_canonical": "24.11.0",
      "distro": "bookworm",
      "platforms": [
        "linux/amd64",
        "linux/arm64"
      ],
      "digest": "sha256:e61f2a8a30a8c86764e0834882f1006db1c289a38898cbc77d1c782f84fae82c"
    },
    {
      "key": "python3.11-nodejs24-slim",
      "python": "3.11",
      "python_canonical": "3.11.14",
      "python_image": "3.11.14-slim",
      "nodejs": "24",
      "nodejs_canonical": "24.11.0",
      "distro": "slim",
      "platforms": [
        "linux/amd64",
        "linux/arm64"
      ],
      "digest": "sha256:4963d7837c3758c6b7196b6f45cf4cf272bb67202e273a54b0b98ecd4c1ea6d3"
    },
    {
      "key": "python3.11-nodejs24-alpine",
      "python": "3.11",
      "python_canonical": "3.11.14",
      "python_image": "3.11.14-alpine",
      "nodejs": "24",
      "nodejs_canonical": "24.11.0",
      "distro": "alpine",
      "platforms": [
        "linux/amd64"
      ],
      "digest": "sha256:a2bfc173ef81d143b8692782d2e5c6a0b9b0f1e0e10cb6d5196fcc89573c474a"
    },
    {
      "key": "python3.11-nodejs22",
      "python": "3.11",
      "python_canonical": "3.11.14",
      "python_image": "3.11.14-trixie",
      "nodejs": "22",
      "nodejs_canonical": "22.21.1",
      "distro": "trixie",
      "platforms": [
        "linux/amd64",
        "linux/arm64"
      ],
      "digest": "sha256:78efec10ac8848068050026cf4c415ac729989eaf0c46fc9d639b09922805263"
    },
    {
      "key": "python3.11-nodejs22-bookworm",
      "python": "3.11",
      "python_canonical": "3.11.14",
      "python_image": "3.11.14-bookworm",
      "nodejs": "22",
      "nodejs_canonical": "22.21.1",
      "distro": "bookworm",
      "platforms": [
        "linux/amd64",
        "linux/arm64"
      ],
      "digest": "sha256:9f6a26a2a13e9fe1e53061a2df236d4b4c51c3cf99c531f24bf920aa7ac1236a"
    },
    {
      "key": "python3.11-nodejs22-slim",
      "python": "3.11",
      "python_canonical": "3.11.14",
      "python_image": "3.11.14-slim",
      "nodejs": "22",
      "nodejs_canonical": "22.21.1",
      "distro": "slim",
      "platforms": [
        "linux/amd64",
        "linux/arm64"
      ],
      "digest": "sha256:df83795a572dc6eea68bcd3d48a2871e6fbd8d35e88b0cd607bcd90fb8c4fa92"
    },
    {
      "key": "python3.11-nodejs22-alpine",
      "python": "3.11",
      "python_canonical": "3.11.14",
      "python_image": "3.11.14-alpine",
      "nodejs": "22",
      "nodejs_canonical": "22.21.1",
      "distro": "alpine",
      "platforms": [
        "linux/amd64"
      ],
      "digest": "sha256:31a8ae2a8b12e76f2b5a469f0847b423c035aa5b1a5b72f1298586aa320b4b17"
    },
    {
      "key": "python3.11-nodejs20",
      "python": "3.11",
      "python_canonical": "3.11.14",
      "python_image": "3.11.14-trixie",
      "nodejs": "20",
      "nodejs_canonical": "20.19.5",
      "distro": "trixie",
      "platforms": [
        "linux/amd64",
        "linux/arm64"
      ],
      "digest": "sha256:0f380e964749897db3dad52ec23dfdcdb187141e395bcf8e155a78a1d7442b75"
    },
    {
      "key": "python3.11-nodejs20-bookworm",
      "python": "3.11",
      "python_canonical": "3.11.14",
      "python_image": "3.11.14-bookworm",
      "nodejs": "20",
      "nodejs_canonical": "20.19.5",
      "distro": "bookworm",
      "platforms": [
        "linux/amd64",
        "linux/arm64"
      ],
      "digest": "sha256:8aa9952190c6d66281da6ad502283a3ea6754da0ab733c4485beacc4cbcd0086"
    },
    {
      "key": "python3.11-nodejs20-slim",
      "python": "3.11",
      "python_canonical": "3.11.14",
      "python_image": "3.11.14-slim",
      "nodejs": "20",
      "nodejs_canonical": "20.19.5",
      "distro": "slim",
      "platforms": [
        "linux/amd64",
        "linux/arm64"
      ],
      "digest": "sha256:e46003e428475009fc391f541bf0dbd9fcb60570c66665fb7ae8a0bbc3c051e4"
    },
    {
      "key": "python3.11-nodejs20-alpine",
      "python": "3.11",
      "python_canonical": "3.11.14",
      "python_image": "3.11.14-alpine",
      "nodejs": "20",
      "nodejs_canonical": "20.19.5",
      "distro": "alpine",
      "platforms": [
        "linux/amd64"
      ],
      "digest": "sha256:bfc5ce7147a17929d426973aa45168f3c094e2c9a2dc787c489432412d473550"
    },
    {
      "key": "python3.10-nodejs25",
      "python": "3.10",
      "python_canonical": "3.10.19",
      "python_image": "3.10.19-trixie",
      "nodejs": "25",
      "nodejs_canonical": "25.1.0",
      "distro": "trixie",
      "platforms": [
        "linux/amd64",
        "linux/arm64"
      ],
      "digest": "sha256:f4e2eb1327e1751ffaf56a98fc5615f603f6d4b2e75472e13fa7c33da59cdca9"
    },
    {
      "key": "python3.10-nodejs25-bookworm",
      "python": "3.10",
      "python_canonical": "3.10.19",
      "python_image": "3.10.19-bookworm",
      "nodejs": "25",
      "nodejs_canonical": "25.1.0",
      "distro": "bookworm",
      "platforms": [
        "linux/amd64",
        "linux/arm64"
      ],
      "digest": "sha256:0b9de29d2d4b49fb740b23093a638218ffc000f2a5534263dbc4e92de086e1f3"
    },
    {
      "key": "python3.10-nodejs25-slim",
      "python": "3.10",
      "python_canonical": "3.10.19",
      "python_image": "3.10.19-slim",
      "nodejs": "25",
      "nodejs_canonical": "25.1.0",
      "distro": "slim",
      "platforms": [
        "linux/amd64",
        "linux/arm64"
      ],
      "digest": "sha256:06898d885ab2b0f90e83ddbe7b8d89e3f4c30dca216b147b1805325581fe3185"
    },
    {
      "key": "python3.10-nodejs25-alpine",
      "python": "3.10",
      "python_canonical": "3.10.19",
      "python_image": "3.10.19-alpine",
      "nodejs": "25",
      "nodejs_canonical": "25.1.0",
      "distro": "alpine",
      "platforms": [
        "linux/amd64"
      ],
      "digest": "sha256:3c9fe2d09ba35e8aa8182c36c502757d60c52a352414edd266aa680dee2027d3"
    },
    {
      "key": "python3.10-nodejs24",
      "python": "3.10",
      "python_canonical": "3.10.19",
      "python_image": "3.10.19-trixie",
      "nodejs": "24",
      "nodejs_canonical": "24.11.0",
      "distro": "trixie",
      "platforms": [
        "linux/amd64",
        "linux/arm64"
      ],
      "digest": "sha256:a4a4d67040c5aedd508f6fdad24014c878d374838b0bc2de44dfa5763c854e7b"
    },
    {
      "key": "python3.10-nodejs24-bookworm",
      "python": "3.10",
      "python_canonical": "3.10.19",
      "python_image": "3.10.19-bookworm",
      "nodejs": "24",
      "nodejs_canonical": "24.11.0",
      "distro": "bookworm",
      "platforms": [
        "linux/amd64",
        "linux/arm64"
      ],
      "digest": "sha256:3abcd90d161ba179c499de5437e3f94477629a94d14cb28f6dd4beaa8f8d8555"
    },
    {
      "key": "python3.10-nodejs24-slim",
      "python": "3.10",
      "python_canonical": "3.10.19",
      "python_image": "3.10.19-slim",
      "nodejs": "24",
      "nodejs_canonical": "24.11.0",
      "distro": "slim",
      "platforms": [
        "linux/amd64",
        "linux/arm64"
      ],
      "digest": "sha256:5d5da781100bb0aff613e5bd16a4a60e35faf308ec82b61d7ee5f9600b48cad4"
    },
    {
      "key": "python3.10-nodejs24-alpine",
      "python": "3.10",
      "python_canonical": "3.10.19",
      "python_image": "3.10.19-alpine",
      "nodejs": "24",
      "nodejs_canonical": "24.11.0",
      "distro": "alpine",
      "platforms": [
        "linux/amd64"
      ],
      "digest": "sha256:539be2517727f5a3792ad5f34d3be8c9b6453585d25bd636bd9dda0c3494da9a"
    },
    {
      "key": "python3.10-nodejs22",
      "python": "3.10",
      "python_canonical": "3.10.19",
      "python_image": "3.10.19-trixie",
      "nodejs": "22",
      "nodejs_canonical": "22.21.1",
      "distro": "trixie",
      "platforms": [
        "linux/amd64",
        "linux/arm64"
      ],
      "digest": "sha256:aaf4dbb8fbbcf48fb32f520e4005c1c3b429471d3a8284020cfd0ee14ea45d63"
    },
    {
      "key": "python3.10-nodejs22-bookworm",
      "python": "3.10",
      "python_canonical": "3.10.19",
      "python_image": "3.10.19-bookworm",
      "nodejs": "22",
      "nodejs_canonical": "22.21.1",
      "distro": "bookworm",
      "platforms": [
        "linux/amd64",
        "linux/arm64"
      ],
      "digest": "sha256:3f855906eb0c2cf720bad7357a0cd9908d5e070babdd907d731a4d83c9707dee"
    },
    {
      "key": "python3.10-nodejs22-slim",
      "python": "3.10",
      "python_canonical": "3.10.19",
      "python_image": "3.10.19-slim",
      "nodejs": "22",
      "nodejs_canonical": "22.21.1",
      "distro": "slim",
      "platforms": [
        "linux/amd64",
        "linux/arm64"
      ],
      "digest": "sha256:027851942e0d1cac5198f5ecb63a968988f52ecdec2ab75b0f6a79b36c0e5879"
    },
    {
      "key": "python3.10-nodejs22-alpine",
      "python": "3.10",
      "python_canonical": "3.10.19",
      "python_image": "3.10.19-alpine",
      "nodejs": "22",
      "nodejs_canonical": "22.21.1",
      "distro": "alpine",
      "platforms": [
        "linux/amd64"
      ],
      "digest": "sha256:9200358cd3be386c90f183ee6121ffe78704a169c99ddf652c4c5012241478bc"
    },
    {
      "key": "python3.10-nodejs20",
      "python": "3.10",
      "python_canonical": "3.10.19",
      "python_image": "3.10.19-trixie",
      "nodejs": "20",
      "nodejs_canonical": "20.19.5",
      "distro": "trixie",
      "platforms": [
        "linux/amd64",
        "linux/arm64"
      ],
      "digest": "sha256:6c55938d4db653862ca95c8a0be07882b0fa59d278d7800da0b600c9499e7163"
    },
    {
      "key": "python3.10-nodejs20-bookworm",
      "python": "3.10",
      "python_canonical": "3.10.19",
      "python_image": "3.10.19-bookworm",
      "nodejs": "20",
      "nodejs_canonical": "20.19.5",
      "distro": "bookworm",
      "platforms": [
        "linux/amd64",
        "linux/arm64"
      ],
      "digest": "sha256:b1d103436a1e6bc16703d56cff937025a55785b0bc3c15a75fe2e09e70be2dc1"
    },
    {
      "key": "python3.10-nodejs20-slim",
      "python": "3.10",
      "python_canonical": "3.10.19",
      "python_image": "3.10.19-slim",
      "nodejs": "20",
      "nodejs_canonical": "20.19.5",
      "distro": "slim",
      "platforms": [
        "linux/amd64",
        "linux/arm64"
      ],
      "digest": "sha256:c43938ab13ef32716029bd5cff5478789a217d3f8ebd160c0725d160be4c04cf"
    },
    {
      "key": "python3.10-nodejs20-alpine",
      "python": "3.10",
      "python_canonical": "3.10.19",
      "python_image": "3.10.19-alpine",
      "nodejs": "20",
      "nodejs_canonical": "20.19.5",
      "distro": "alpine",
      "platforms": [
        "linux/amd64"
      ],
      "digest": "sha256:efce375211d17e798299004de14ccefd516641f9143b171843b2bde4dc85608c"
    }
  ]
}